LICENSE
README.md
pyproject.toml
setup.cfg
setup.py
mobio/sdks/media/__init__.py
mobio/sdks/media/config.py
mobio/sdks/media/constant.py
mobio/sdks/media/custom_mimetypes.py
mobio/sdks/media/dir.py
mobio/sdks/media/merchant_config.py
mobio/sdks/media/mobio_media_sdk.py
mobio/sdks/media/utils.py
mobio_media_sdk_test.egg-info/PKG-INFO
mobio_media_sdk_test.egg-info/SOURCES.txt
mobio_media_sdk_test.egg-info/dependency_links.txt
mobio_media_sdk_test.egg-info/namespace_packages.txt
mobio_media_sdk_test.egg-info/requires.txt
mobio_media_sdk_test.egg-info/top_level.txt